shd1/__init__.py
shd1/main.py
shd1-0.0.2.dist-info/METADATA
shd1-0.0.2.dist-info/WHEEL
shd1-0.0.2.dist-info/licenses/LICENSE
shd1-0.0.2.dist-info/RECORD
