Metadata-Version: 2.4
Name: shd1
Version: 0.0.2
Summary: This library creates the ability to use a new hash function for stronger data protection.
Author-email: Daniil <mineshaftt@yandex.ru>
License-File: LICENSE
Classifier: License :: OSI Approved :: MIT License
Classifier: Operating System :: OS Independent
Classifier: Programming Language :: Python :: 3
Requires-Python: >=3.10.0
